gmock_vendor/_dummy.cpython-310-x86_64-linux-gnu.so
ros_gmock_vendor-1.15.1.data/data/share/gmock_vendor/package.xml
ros_gmock_vendor-1.15.1.data/data/share/gmock_vendor/cmake/gmock_vendorConfig.cmake
ros_gmock_vendor-1.15.1.data/data/src/gmock_vendor/CMakeLists.txt
ros_gmock_vendor-1.15.1.data/data/src/gmock_vendor/include/gmock/gmock-actions.h
ros_gmock_vendor-1.15.1.data/data/src/gmock_vendor/include/gmock/gmock-cardinalities.h
ros_gmock_vendor-1.15.1.data/data/src/gmock_vendor/include/gmock/gmock-function-mocker.h
ros_gmock_vendor-1.15.1.data/data/src/gmock_vendor/include/gmock/gmock-matchers.h
ros_gmock_vendor-1.15.1.data/data/src/gmock_vendor/include/gmock/gmock-more-actions.h
ros_gmock_vendor-1.15.1.data/data/src/gmock_vendor/include/gmock/gmock-more-matchers.h
ros_gmock_vendor-1.15.1.data/data/src/gmock_vendor/include/gmock/gmock-nice-strict.h
ros_gmock_vendor-1.15.1.data/data/src/gmock_vendor/include/gmock/gmock-spec-builders.h
ros_gmock_vendor-1.15.1.data/data/src/gmock_vendor/include/gmock/gmock.h
ros_gmock_vendor-1.15.1.data/data/src/gmock_vendor/include/gmock/internal/gmock-internal-utils.h
ros_gmock_vendor-1.15.1.data/data/src/gmock_vendor/include/gmock/internal/gmock-port.h
ros_gmock_vendor-1.15.1.data/data/src/gmock_vendor/include/gmock/internal/gmock-pp.h
ros_gmock_vendor-1.15.1.data/data/src/gmock_vendor/include/gmock/internal/custom/README.md
ros_gmock_vendor-1.15.1.data/data/src/gmock_vendor/include/gmock/internal/custom/gmock-generated-actions.h
ros_gmock_vendor-1.15.1.data/data/src/gmock_vendor/include/gmock/internal/custom/gmock-matchers.h
ros_gmock_vendor-1.15.1.data/data/src/gmock_vendor/include/gmock/internal/custom/gmock-port.h
ros_gmock_vendor-1.15.1.data/data/src/gmock_vendor/src/gmock-all.cc
ros_gmock_vendor-1.15.1.data/data/src/gmock_vendor/src/gmock-cardinalities.cc
ros_gmock_vendor-1.15.1.data/data/src/gmock_vendor/src/gmock-internal-utils.cc
ros_gmock_vendor-1.15.1.dist-info/METADATA
ros_gmock_vendor-1.15.1.dist-info/WHEEL
ros_gmock_vendor-1.15.1.dist-info/top_level.txt
ros_gmock_vendor-1.15.1.dist-info/RECORD
