Metadata-Version: 2.4
Name: ros-gmock-vendor
Version: 1.15.1
Summary: A ROS package providing Google's gMock C++ mocking framework to facilitate robust system design and writing better tests.
Requires-Dist: ros-gtest-vendor~=1.15.1
Dynamic: description
Dynamic: description-content-type
Dynamic: requires-dist
Dynamic: summary
